{
    "footonsat": [
        {
            "compet": "Spanish La Liga 2 - Week 29",
            "match": " Cádiz vs Real Zaragoza ",
            "flags": {
                "team1": "spain",
                "team2": "spain"
            },
            "time": "19:30",
            "date": "2026-03-06"
        },
        {
            "channel": "Arena Sport 1x2 Srbija",
            "sat": "Astra 3C 23.5°e",
            "freq": "12402 V 30000 - 3/4",
            "encry": "MPEG-4 Conax",
            "link": "",
            "related_to": " Cádiz vs Real Zaragoza "
        },
        {
            "channel": "Arena Sport 5 BiH HD",
            "sat": "Astra 3B 23.5°e",
            "freq": "0000 0",
            "encry": "HD Conax",
            "link": "",
            "related_to": " Cádiz vs Real Zaragoza "
        },
        {
            "channel": "Arena Sport 7 Hrvatska HD",
            "sat": "Eutelsat 16A 16.0°e",
            "freq": "11595 H 30000 - 3/4",
            "encry": "HD Conax",
            "link": "",
            "related_to": " Cádiz vs Real Zaragoza "
        },
        {
            "channel": "beIN Sports 2 HD",
            "sat": "Measat 3b 91.5°e",
            "freq": "10732 V 30000 - 5/6",
            "encry": "HD VideoGuard",
            "link": "",
            "related_to": " Cádiz vs Real Zaragoza "
        },
        {
            "channel": "DAZN España",
            "sat": "* IPTV/Stream 0.0°",
            "freq": "0000",
            "encry": "",
            "link": "",
            "related_to": " Cádiz vs Real Zaragoza "
        },
        {
            "channel": "LaLiga Hypermotion HD",
            "sat": "Astra 1M 19.2°e",
            "freq": "10936 V 22000 - 2/3",
            "encry": "HD NagraVision",
            "link": "",
            "related_to": " Cádiz vs Real Zaragoza "
        },
        {
            "channel": "Megogo Futbol 5",
            "sat": "* IPTV/Stream 0.0°",
            "freq": "0000",
            "encry": "",
            "link": "",
            "related_to": " Cádiz vs Real Zaragoza "
        },
        {
            "channel": "Nova Sports 2 Hellas HD",
            "sat": "Hotbird 13F 13.0°e",
            "freq": "12130 H 27500 - 3/4",
            "encry": "HD Irdeto",
            "link": "",
            "related_to": " Cádiz vs Real Zaragoza "
        },
        {
            "channel": "Premier Sports 2 Ireland HD",
            "sat": "Astra 2F 28.2°e",
            "freq": "12188 H 27500 - 3/4",
            "encry": "HD VideoGuard",
            "link": "",
            "related_to": " Cádiz vs Real Zaragoza "
        },
        {
            "channel": "Premier Sports 2 UK HD",
            "sat": "Astra 2G 28.2°e",
            "freq": "11671 H 23000 - 2/3",
            "encry": "HD VideoGuard",
            "link": "",
            "related_to": " Cádiz vs Real Zaragoza "
        },
        {
            "channel": "Premier Sports GB Player HD 📺",
            "sat": "* IPTV/Stream 0.0°",
            "freq": "0000 0",
            "encry": "",
            "link": "https://www.premiersports.com/fr/live-now-on-demand",
            "related_to": " Cádiz vs Real Zaragoza "
        },
        {
            "channel": "Prima Sport RO PPV 2",
            "sat": "* IPTV/Stream 0.0°",
            "freq": "0000 0",
            "encry": "",
            "link": "",
            "related_to": " Cádiz vs Real Zaragoza "
        },
        {
            "compet": "Spanish La Liga 2 - Week 29",
            "match": " Huesca vs Albacete ",
            "flags": {
                "team1": "spain",
                "team2": "spain"
            },
            "time": "15:15",
            "date": "2026-03-07"
        },
        {
            "channel": "DAZN España",
            "sat": "* IPTV/Stream 0.0°",
            "freq": "0000",
            "encry": "",
            "link": "",
            "related_to": " Huesca vs Albacete "
        },
        {
            "compet": "Spanish La Liga 2 - Week 29",
            "match": " Real Sociedad II vs Castellón ",
            "flags": {
                "team1": "spain",
                "team2": "spain"
            },
            "time": "15:15",
            "date": "2026-03-07"
        },
        {
            "channel": "DAZN España",
            "sat": "* IPTV/Stream 0.0°",
            "freq": "0000",
            "encry": "",
            "link": "",
            "related_to": " Real Sociedad II vs Castellón "
        },
        {
            "compet": "Spanish La Liga 2 - Week 29",
            "match": " Burgos vs Mirandés ",
            "flags": {
                "team1": "spain",
                "team2": "spain"
            },
            "time": "17:30",
            "date": "2026-03-07"
        },
        {
            "channel": "DAZN España",
            "sat": "* IPTV/Stream 0.0°",
            "freq": "0000",
            "encry": "",
            "link": "",
            "related_to": " Burgos vs Mirandés "
        },
        {
            "compet": "Spanish La Liga 2 - Week 29",
            "match": " Málaga vs Real Valladolid ",
            "flags": {
                "team1": "spain",
                "team2": "spain"
            },
            "time": "20:00",
            "date": "2026-03-07"
        },
        {
            "channel": "Arena Sport 3 BiH HD",
            "sat": "Astra 3B 23.5°e",
            "freq": "11895 V 30000 - 3/4",
            "encry": "HD Conax",
            "link": "",
            "related_to": " Málaga vs Real Valladolid "
        },
        {
            "channel": "Arena Sport 4 Srbija HD",
            "sat": "Astra 3B 23.5°e",
            "freq": "11798 H 30000 - 3/4",
            "encry": "HD Conax",
            "link": "",
            "related_to": " Málaga vs Real Valladolid "
        },
        {
            "channel": "Arena Sport 7 Hrvatska HD",
            "sat": "Eutelsat 16A 16.0°e",
            "freq": "11595 H 30000 - 3/4",
            "encry": "HD Conax",
            "link": "",
            "related_to": " Málaga vs Real Valladolid "
        },
        {
            "channel": "DAZN España",
            "sat": "* IPTV/Stream 0.0°",
            "freq": "0000",
            "encry": "",
            "link": "",
            "related_to": " Málaga vs Real Valladolid "
        },
        {
            "channel": "Megogo Futbol 5",
            "sat": "* IPTV/Stream 0.0°",
            "freq": "0000",
            "encry": "",
            "link": "",
            "related_to": " Málaga vs Real Valladolid "
        },
        {
            "channel": "Prima Sport RO PPV 3",
            "sat": "* IPTV/Stream 0.0°",
            "freq": "0000 0",
            "encry": "",
            "link": "",
            "related_to": " Málaga vs Real Valladolid "
        },
        {
            "channel": "TV2 Play Norge📺",
            "sat": "* IPTV/Stream 0.0°",
            "freq": "0000",
            "encry": "",
            "link": "https://play.tv2.no/sport",
            "related_to": " Málaga vs Real Valladolid "
        },
        {
            "channel": "TV2 Sport Premium 2 HD",
            "sat": "Thor 6 5.0°e",
            "freq": "11385 V 30000 - 3/4",
            "encry": "HD VideoGuard",
            "link": "",
            "related_to": " Málaga vs Real Valladolid "
        },
        {
            "compet": "Spanish La Liga 2 - Week 29",
            "match": " Las Palmas vs Ceuta ",
            "flags": {
                "team1": "spain",
                "team2": "spain"
            },
            "time": "13:00",
            "date": "2026-03-08"
        },
        {
            "channel": "DAZN España",
            "sat": "* IPTV/Stream 0.0°",
            "freq": "0000",
            "encry": "",
            "link": "",
            "related_to": " Las Palmas vs Ceuta "
        },
        {
            "compet": "Spanish La Liga 2 - Week 29",
            "match": " Andorra vs Sporting Gijón ",
            "flags": {
                "team1": "spain",
                "team2": "spain"
            },
            "time": "15:15",
            "date": "2026-03-08"
        },
        {
            "channel": "DAZN España",
            "sat": "* IPTV/Stream 0.0°",
            "freq": "0000",
            "encry": "",
            "link": "",
            "related_to": " Andorra vs Sporting Gijón "
        },
        {
            "compet": "Spanish La Liga 2 - Week 29",
            "match": " Racing Santander vs Córdoba ",
            "flags": {
                "team1": "spain",
                "team2": "spain"
            },
            "time": "17:30",
            "date": "2026-03-08"
        },
        {
            "channel": "DAZN España",
            "sat": "* IPTV/Stream 0.0°",
            "freq": "0000",
            "encry": "",
            "link": "",
            "related_to": " Racing Santander vs Córdoba "
        },
        {
            "compet": "Spanish La Liga 2 - Week 29",
            "match": " Leganés vs Eibar ",
            "flags": {
                "team1": "spain",
                "team2": "spain"
            },
            "time": "17:30",
            "date": "2026-03-08"
        },
        {
            "channel": "DAZN España",
            "sat": "* IPTV/Stream 0.0°",
            "freq": "0000",
            "encry": "",
            "link": "",
            "related_to": " Leganés vs Eibar "
        },
        {
            "compet": "Spanish La Liga 2 - Week 29",
            "match": " Deportivo La Coruña vs Granada ",
            "flags": {
                "team1": "spain",
                "team2": "spain"
            },
            "time": "20:00",
            "date": "2026-03-08"
        },
        {
            "channel": "Arena Sport 1 BiH HD",
            "sat": "Astra 3B 23.5°e",
            "freq": "11720 H 30000 - 3/4",
            "encry": "HD Conax",
            "link": "",
            "related_to": " Deportivo La Coruña vs Granada "
        },
        {
            "channel": "Arena Sport 1x2 Srbija",
            "sat": "Astra 3C 23.5°e",
            "freq": "12402 V 30000 - 3/4",
            "encry": "MPEG-4 Conax",
            "link": "",
            "related_to": " Deportivo La Coruña vs Granada "
        },
        {
            "channel": "Arena Sport 7 Hrvatska HD",
            "sat": "Eutelsat 16A 16.0°e",
            "freq": "11595 H 30000 - 3/4",
            "encry": "HD Conax",
            "link": "",
            "related_to": " Deportivo La Coruña vs Granada "
        },
        {
            "channel": "DAZN 2 Portugal HD",
            "sat": "Hispasat 30W-5 30.0°w",
            "freq": "12246 H 27500 - 3/4",
            "encry": "HD NagraVision",
            "link": "",
            "related_to": " Deportivo La Coruña vs Granada "
        },
        {
            "channel": "DAZN España",
            "sat": "* IPTV/Stream 0.0°",
            "freq": "0000",
            "encry": "",
            "link": "",
            "related_to": " Deportivo La Coruña vs Granada "
        },
        {
            "channel": "Megogo Futbol 5",
            "sat": "* IPTV/Stream 0.0°",
            "freq": "0000",
            "encry": "",
            "link": "",
            "related_to": " Deportivo La Coruña vs Granada "
        },
        {
            "channel": "Prima Sport RO PPV 1",
            "sat": "* IPTV/Stream 0.0°",
            "freq": "0000 0",
            "encry": "",
            "link": "",
            "related_to": " Deportivo La Coruña vs Granada "
        },
        {
            "compet": "Spanish La Liga 2 - Week 29",
            "match": " Almería vs Cultural Leonesa ",
            "flags": {
                "team1": "spain",
                "team2": "spain"
            },
            "time": "19:30",
            "date": "2026-03-09"
        },
        {
            "channel": "Arena Sport 2 Srbija HD",
            "sat": "Astra 3B 23.5°e",
            "freq": "11798 H 30000 - 3/4",
            "encry": "HD Conax",
            "link": "",
            "related_to": " Almería vs Cultural Leonesa "
        },
        {
            "channel": "Arena Sport 6 Hrvatska HD",
            "sat": "Eutelsat 16A 16.0°e",
            "freq": "11554 V 30000 - 5/6",
            "encry": "HD Conax",
            "link": "",
            "related_to": " Almería vs Cultural Leonesa "
        },
        {
            "channel": "beIN Sports MENA 4 HD",
            "sat": "Eshail 2 25.5°e",
            "freq": "10810 V 27500 - 2/3",
            "encry": "HD Irdeto",
            "link": "",
            "related_to": " Almería vs Cultural Leonesa "
        },
        {
            "channel": "Cytavision Sports 7 HD",
            "sat": "* IPTV/Stream 0.0°",
            "freq": "0000",
            "encry": "",
            "link": "",
            "related_to": " Almería vs Cultural Leonesa "
        },
        {
            "channel": "DAZN España",
            "sat": "* IPTV/Stream 0.0°",
            "freq": "0000",
            "encry": "",
            "link": "",
            "related_to": " Almería vs Cultural Leonesa "
        },
        {
            "channel": "Nova Sport 3 Czech HD",
            "sat": "Astra 3B 23.5°e",
            "freq": "11934 V 27500 - 3/4",
            "encry": "HD Conax",
            "link": "",
            "related_to": " Almería vs Cultural Leonesa "
        },
        {
            "channel": "Nova Sports Start Hellas HD",
            "sat": "Hotbird 13F 13.0°e",
            "freq": "11804 V 29700 - 3/4",
            "encry": "HD Irdeto",
            "link": "",
            "related_to": " Almería vs Cultural Leonesa "
        },
        {
            "channel": "Prima Sport RO PPV 1",
            "sat": "* IPTV/Stream 0.0°",
            "freq": "0000 0",
            "encry": "",
            "link": "",
            "related_to": " Almería vs Cultural Leonesa "
        },
        {
            "channel": "S Sport+ Streaming",
            "sat": "* IPTV/Stream 0.0°",
            "freq": "0000",
            "encry": "",
            "link": "",
            "related_to": " Almería vs Cultural Leonesa "
        },
        {
            "compet": "Spanish La Liga 2 - Week 30",
            "match": " Mirandés vs Cádiz ",
            "flags": {
                "team1": "spain",
                "team2": "spain"
            },
            "time": "19:30",
            "date": "2026-03-13"
        },
        {
            "channel": "Arena Sport 6 Hrvatska HD",
            "sat": "Eutelsat 16A 16.0°e",
            "freq": "11554 V 30000 - 5/6",
            "encry": "HD Conax",
            "link": "",
            "related_to": " Mirandés vs Cádiz "
        },
        {
            "channel": "DAZN España",
            "sat": "* IPTV/Stream 0.0°",
            "freq": "0000",
            "encry": "",
            "link": "",
            "related_to": " Mirandés vs Cádiz "
        },
        {
            "compet": "Spanish La Liga 2 - Week 30",
            "match": " Cultural Leonesa vs Racing Santander ",
            "flags": {
                "team1": "spain",
                "team2": "spain"
            },
            "time": "15:15",
            "date": "2026-03-14"
        },
        {
            "channel": "DAZN España",
            "sat": "* IPTV/Stream 0.0°",
            "freq": "0000",
            "encry": "",
            "link": "",
            "related_to": " Cultural Leonesa vs Racing Santander "
        },
        {
            "compet": "Spanish La Liga 2 - Week 30",
            "match": " Real Zaragoza vs Almería ",
            "flags": {
                "team1": "spain",
                "team2": "spain"
            },
            "time": "17:30",
            "date": "2026-03-14"
        },
        {
            "channel": "DAZN España",
            "sat": "* IPTV/Stream 0.0°",
            "freq": "0000",
            "encry": "",
            "link": "",
            "related_to": " Real Zaragoza vs Almería "
        },
        {
            "compet": "Spanish La Liga 2 - Week 30",
            "match": " Real Valladolid vs Leganés ",
            "flags": {
                "team1": "spain",
                "team2": "spain"
            },
            "time": "17:30",
            "date": "2026-03-14"
        },
        {
            "channel": "DAZN España",
            "sat": "* IPTV/Stream 0.0°",
            "freq": "0000",
            "encry": "",
            "link": "",
            "related_to": " Real Valladolid vs Leganés "
        },
        {
            "compet": "Spanish La Liga 2 - Week 30",
            "match": " Ceuta vs Deportivo La Coruña ",
            "flags": {
                "team1": "spain",
                "team2": "spain"
            },
            "time": "20:00",
            "date": "2026-03-14"
        },
        {
            "channel": "DAZN España",
            "sat": "* IPTV/Stream 0.0°",
            "freq": "0000",
            "encry": "",
            "link": "",
            "related_to": " Ceuta vs Deportivo La Coruña "
        },
        {
            "compet": "Spanish La Liga 2 - Week 30",
            "match": " Córdoba vs Real Sociedad II ",
            "flags": {
                "team1": "spain",
                "team2": "spain"
            },
            "time": "13:00",
            "date": "2026-03-15"
        },
        {
            "channel": "DAZN España",
            "sat": "* IPTV/Stream 0.0°",
            "freq": "0000",
            "encry": "",
            "link": "",
            "related_to": " Córdoba vs Real Sociedad II "
        },
        {
            "compet": "Spanish La Liga 2 - Week 30",
            "match": " Granada vs Andorra ",
            "flags": {
                "team1": "spain",
                "team2": "spain"
            },
            "time": "15:15",
            "date": "2026-03-15"
        },
        {
            "channel": "DAZN España",
            "sat": "* IPTV/Stream 0.0°",
            "freq": "0000",
            "encry": "",
            "link": "",
            "related_to": " Granada vs Andorra "
        },
        {
            "compet": "Spanish La Liga 2 - Week 30",
            "match": " Eibar vs Burgos ",
            "flags": {
                "team1": "spain",
                "team2": "spain"
            },
            "time": "17:30",
            "date": "2026-03-15"
        },
        {
            "channel": "DAZN España",
            "sat": "* IPTV/Stream 0.0°",
            "freq": "0000",
            "encry": "",
            "link": "",
            "related_to": " Eibar vs Burgos "
        },
        {
            "compet": "Spanish La Liga 2 - Week 30",
            "match": " Málaga vs Huesca ",
            "flags": {
                "team1": "spain",
                "team2": "spain"
            },
            "time": "17:30",
            "date": "2026-03-15"
        },
        {
            "channel": "DAZN España",
            "sat": "* IPTV/Stream 0.0°",
            "freq": "0000",
            "encry": "",
            "link": "",
            "related_to": " Málaga vs Huesca "
        },
        {
            "compet": "Spanish La Liga 2 - Week 30",
            "match": " Sporting Gijón vs Castellón ",
            "flags": {
                "team1": "spain",
                "team2": "spain"
            },
            "time": "20:00",
            "date": "2026-03-15"
        },
        {
            "channel": "Arena Sport 7 Hrvatska HD",
            "sat": "Eutelsat 16A 16.0°e",
            "freq": "11595 H 30000 - 3/4",
            "encry": "HD Conax",
            "link": "",
            "related_to": " Sporting Gijón vs Castellón "
        },
        {
            "channel": "DAZN España",
            "sat": "* IPTV/Stream 0.0°",
            "freq": "0000",
            "encry": "",
            "link": "",
            "related_to": " Sporting Gijón vs Castellón "
        },
        {
            "compet": "Spanish La Liga 2 - Week 30",
            "match": " Albacete vs Las Palmas ",
            "flags": {
                "team1": "spain",
                "team2": "spain"
            },
            "time": "19:30",
            "date": "2026-03-16"
        },
        {
            "channel": "DAZN España",
            "sat": "* IPTV/Stream 0.0°",
            "freq": "0000",
            "encry": "",
            "link": "",
            "related_to": " Albacete vs Las Palmas "
        }
    ]
}